tahoe_capabilities/__init__.py
tahoe_capabilities/hashutil.py
tahoe_capabilities/parser.py
tahoe_capabilities/predicates.py
tahoe_capabilities/py.typed
tahoe_capabilities/serializer.py
tahoe_capabilities/strategies.py
tahoe_capabilities/types.py
tahoe_capabilities/test/__init__.py
tahoe_capabilities/test/test_capabilities.py
tahoe_capabilities-2023.1.5.dist-info/METADATA
tahoe_capabilities-2023.1.5.dist-info/WHEEL
tahoe_capabilities-2023.1.5.dist-info/top_level.txt
tahoe_capabilities-2023.1.5.dist-info/RECORD
