Metadata-Version: 2.1
Name: tahoe-capabilities
Version: 2023.1.5
Summary: A library for working with Tahoe-LAFS data capability values
Home-page: https://tahoe-lafs.org/
License: GPLv2
Project-URL: Source, https://github.com/tahoe-lafs/tahoe-capabilities
Project-URL: Issues, https://github.com/tahoe-lafs/tahoe-capabilities/issues
Platform: UNKNOWN
Requires-Dist: attrs
Provides-Extra: test
Requires-Dist: twisted ; extra == 'test'
Requires-Dist: hypothesis ; extra == 'test'
